{
  "color": {
    "surface": {
      "neutral": {
        "default": {
          "value": "{color.gray.0}",
          "type": "color",
          "description": "A superfície de nível mais baixo, usada na maioria dos componentes."
        },
        "soft": {
          "value": "{color.gray.100}",
          "type": "color",
          "description": "Use para delinear superfícies sem usar bordas, como em cards neutros."
        },
        "strong": {
          "value": "{color.gray.200}",
          "type": "color",
          "description": "Use para destacar superfícies delineadasda interface, como o estado de hover de um card neutro."
        },
        "inverse": {
          "value": "{color.gray.900}",
          "type": "color",
          "description": "Use em casos em que haja necessidade de alto contraste para destacar o elemento, como um tooltip."
        }
      },
      "accent": {
        "softer": {
          "value": "{color.purple.100}",
          "type": "color",
          "description": "Use para delinear superfícies sem usar bordas."
        },
        "soft": {
          "value": "{color.purple.200}",
          "type": "color",
          "description": "Use para destacar superfícies delineadas da interface."
        },
        "default": {
          "value": "{color.purple.600}",
          "type": "color",
          "description": "Use para indicar elementos interativos de relevância primária, como botões."
        },
        "strong": {
          "value": "{color.purple.700}",
          "type": "color",
          "description": "Use para destacar elementos interativos primários, comoseu estado de hover."
        }
      },
      "info": {
        "softer": {
          "value": "{color.blue.100}",
          "type": "color",
          "description": "Use para delinear superfícies sem usar bordas."
        },
        "soft": {
          "value": "{color.blue.200}",
          "type": "color",
          "description": "Use para destacar superfícies delineadas da interface."
        },
        "default": {
          "value": "{color.blue.600}",
          "type": "color",
          "description": "Use para indicar elementos interativos de relevância primária, como botões."
        },
        "strong": {
          "value": "{color.blue.700}",
          "type": "color",
          "description": "Use para destacar elementos interativos primários, comoseu estado de hover."
        }
      },
      "success": {
        "softer": {
          "value": "{color.green.100}",
          "type": "color",
          "description": "Use para delinear superfícies sem usar bordas."
        },
        "soft": {
          "value": "{color.green.200}",
          "type": "color",
          "description": "Utilize como cor de preenchimento de elementos de maior proeminência na interface, como um card."
        },
        "default": {
          "value": "{color.green.600}",
          "type": "color",
          "description": "Use para indicar elementos interativos de relevância primária, como botões."
        },
        "strong": {
          "value": "{color.green.700}",
          "type": "color",
          "description": "Use para destacar elementos interativos primários, comoseu estado de hover."
        }
      },
      "warning": {
        "softer": {
          "value": "{color.yellow.100}",
          "type": "color",
          "description": "Use para delinear superfícies sem usar bordas."
        },
        "soft": {
          "value": "{color.yellow.200}",
          "type": "color",
          "description": "Use para destacar superfícies delineadas da interface."
        },
        "default": {
          "value": "{color.yellow.500}",
          "type": "color",
          "description": "Use para indicar elementos interativos de relevância primária, como botões."
        },
        "strong": {
          "value": "{color.yellow.600}",
          "type": "color",
          "description": "Use para destacar elementos interativos primários, comoseu estado de hover."
        }
      },
      "danger": {
        "softer": {
          "value": "{color.red.100}",
          "type": "color",
          "description": "Use para delinear superfícies sem usar bordas."
        },
        "soft": {
          "value": "{color.red.200}",
          "type": "color",
          "description": "Use para destacar superfícies delineadas da interface."
        },
        "default": {
          "value": "{color.red.600}",
          "type": "color",
          "description": "Use para indicar elementos interativos de relevância primária, como botões."
        },
        "strong": {
          "value": "{color.red.700}",
          "type": "color",
          "description": "Use para destacar elementos interativos primários, comoseu estado de hover."
        }
      },
      "gradient": {
        "accent": {
          "highlight": {
            "value": "{color.blue.500}",
            "type": "color",
            "description": "Usado como a cor de highlight dos degradês."
          },
          "base": {
            "value": "{color.surface.accent.default}",
            "type": "color",
            "description": "Usado como a cor predominante dos degradês."
          },
          "shade": {
            "value": "{color.surface.accent.strong}",
            "type": "color",
            "description": "Usado como o tom inicial dos degradês."
          }
        },
        "success": {
          "highlight": {
            "value": "{color.green.500}",
            "type": "color",
            "description": "Usado como a cor de highlight dos degradês de valor semântico positivo."
          },
          "base": {
            "value": "{color.surface.success.default}",
            "type": "color",
            "description": "Usado como a cor predominante dos degradês de valor semântico positivo."
          },
          "shade": {
            "value": "{color.surface.success.strong}",
            "type": "color",
            "description": "Usado como o tom inicial dos degradês de valor semântico positivo."
          }
        },
        "danger": {
          "highlight": {
            "value": "{color.pink.500}",
            "type": "color",
            "description": "Usado como a cor de highlight dos degradês de valor semântico negativo."
          },
          "base": {
            "value": "{color.surface.danger.default}",
            "type": "color",
            "description": "Usado como a cor predominante dos degradês de valor semântico negativo."
          },
          "shade": {
            "value": "{color.surface.danger.strong}",
            "type": "color",
            "description": "Usado como o tom inicial dos degradês de valor semântico negativo."
          }
        }
      }
    },
    "border": {
      "neutral": {
        "default": {
          "value": "{color.gray.200}",
          "type": "color",
          "description": "Use para delinear o contornode elementos não-interativos, como cards de conteúdo."
        },
        "interactive": {
          "value": "{color.gray.300}",
          "type": "color",
          "description": "Use para delinear o contornode elementos interativos,como campos de formulário."
        },
        "strong": {
          "value": "{color.gray.500}",
          "type": "color",
          "description": "Use para realçar sutilmenteo contorno de elementos interativos, como seu estadode hover."
        },
        "stronger": {
          "value": "{color.gray.700}",
          "type": "color",
          "description": "Use para destacar o contorno de elementos interativos, como seu estado de focus."
        },
        "inverse": {
          "value": "{color.gray.0}",
          "type": "color",
          "description": "Use para criar um efeito \"cutout\" em elementos posicionado sobre a cor de superfície padrão."
        }
      },
      "accent": {
        "soft": {
          "value": "{color.surface.accent.soft}",
          "type": "color",
          "description": "Use para realçar o contorno de elementos interativos secundários."
        },
        "default": {
          "value": "{color.surface.accent.default}",
          "type": "color",
          "description": "Use para realçar o contorno de elementos interativos primários."
        }
      },
      "info": {
        "soft": {
          "value": "{color.surface.info.soft}",
          "type": "color",
          "description": "Use para realçar o contorno de elementos interativos secundários que indiquem uma situação ou estado informativo."
        },
        "default": {
          "value": "{color.surface.info.default}",
          "type": "color",
          "description": "Use para realçar o contorno de elementos interativos que indiquem uma situação ou estado informativo."
        }
      },
      "success": {
        "soft": {
          "value": "{color.surface.success.soft}",
          "type": "color",
          "description": "Use para realçar o contorno de elementos interativos secundários que indiquem uma situação ou estado positivo."
        },
        "default": {
          "value": "{color.surface.success.default}",
          "type": "color",
          "description": "Use para realçar o contorno de elementos interativos que indiquem uma situação ou estado positivo."
        }
      },
      "warning": {
        "soft": {
          "value": "{color.surface.warning.soft}",
          "type": "color",
          "description": "Use para realçar o contorno de elementos interativos secundários que indiquem um estado de suspense ou não-crítico."
        },
        "default": {
          "value": "{color.surface.warning.strong}",
          "type": "color",
          "description": "Use para realçar o contorno de elementos interativos que indiquem um estado de suspense ou não-crítico."
        }
      },
      "danger": {
        "soft": {
          "value": "{color.surface.danger.soft}",
          "type": "color",
          "description": "Use para realçar o contorno de elementos interativos secundários que indiquem uma situação ou estado negativo."
        },
        "default": {
          "value": "{color.surface.danger.default}",
          "type": "color",
          "description": "Use para realçar o contorno de elementos interativos que indiquem uma situação ou estado negativo."
        }
      }
    },
    "text": {
      "neutral": {
        "soft": {
          "value": "{color.gray.500}",
          "type": "color",
          "description": "Use em textos de relevância secundária, como textos de apoio, legendas e textos legais."
        },
        "default": {
          "value": "{color.gray.800}",
          "type": "color",
          "description": "Cor padrão para os textos em nossas interfaces."
        },
        "strong": {
          "value": "{color.gray.900}",
          "type": "color",
          "description": "Use para realçar textose em elementos textuaisde relevância primária,como títulos."
        },
        "inverse": {
          "value": "{color.gray.0}",
          "type": "color",
          "description": "Use em casos especiais em que haja a necessidade que a cor do texto seja igual à cor de fundo da interface."
        }
      },
      "accent": {
        "base": {
          "value": "{color.purple.600}",
          "type": "color",
          "description": "Use em textos de elementos interativos, como links e botões."
        },
        "strong": {
          "value": "{color.purple.700}",
          "type": "color",
          "description": "Use para realçar textosde elementos interativos,como seu estado de hover."
        }
      },
      "info": {
        "base": {
          "value": "{color.blue.600}",
          "type": "color",
          "description": "Use em textos de elementos interativos informativos, como links e botões."
        },
        "strong": {
          "value": "{color.blue.700}",
          "type": "color",
          "description": "Use para realçar textos de elementos interativos informativos, como seu estadode hover."
        },
        "default": {
          "value": "{color.blue.900}",
          "type": "color",
          "description": "Use em passagens de textos informativos não-interativos."
        }
      },
      "success": {
        "base": {
          "value": "{color.green.600}",
          "type": "color",
          "description": "Use em textos de elementos interativospositivos, como links e botões em uma mensagem de sucesso."
        },
        "strong": {
          "value": "{color.green.700}",
          "type": "color",
          "description": "Use para realçar textos de elementos interativos positivos, como o estadode hover de um link."
        },
        "default": {
          "value": "{color.green.900}",
          "type": "color",
          "description": "Use em textos não-interativos de conotação positiva, como mensagens de sucesso."
        }
      },
      "warning": {
        "base": {
          "value": "{color.yellow.700}",
          "type": "color",
          "description": "Use em textos de elementos interativosnão-críticos, como links e botões em uma mensagem de alerta."
        },
        "strong": {
          "value": "{color.yellow.800}",
          "type": "color",
          "description": "Use para realçar textos de elementos interativos não-críticos, como o estadode hover de um link."
        },
        "default": {
          "value": "{color.yellow.900}",
          "type": "color",
          "description": "Use em textos não-interativos não-críticos, como mensagens de alerta."
        }
      },
      "danger": {
        "base": {
          "value": "{color.red.600}",
          "type": "color",
          "description": "Use em textos de elementos interativosnegativos, como links e botões em uma mensagem de erro."
        },
        "strong": {
          "value": "{color.red.700}",
          "type": "color",
          "description": "Use para realçar textos de elementos interativos negativos, como o estadode hover de um link."
        },
        "default": {
          "value": "{color.red.900}",
          "type": "color",
          "description": "Use em textos não-interativos de conotação negativa, como mensagens de erro."
        }
      }
    },
    "icon": {
      "neutral": {
        "soft": {
          "value": "{color.border.neutral.interactive}",
          "type": "color",
          "description": "Use em ícones de relevância secundária."
        },
        "default": {
          "value": "{color.text.neutral.default}",
          "type": "color",
          "description": "Cor padrão para ícones."
        },
        "strong": {
          "value": "{color.text.neutral.strong}",
          "type": "color",
          "description": "Use para realçar ícones de relevância primária, como em seu estado de hover."
        },
        "inverse": {
          "value": "{color.text.neutral.inverse}",
          "type": "color",
          "description": "Use em casos especiais em que haja a necessidade que a cor do ícone seja igual à cor de fundo da interface."
        }
      },
      "semantic": {
        "accent": {
          "value": "{color.text.accent.base}",
          "type": "color",
          "description": "Use em ícones de elementos interativos."
        },
        "info": {
          "value": "{color.text.info.base}",
          "type": "color",
          "description": "Use em ícones de elementos informativos."
        },
        "success": {
          "value": "{color.text.success.base}",
          "type": "color",
          "description": "Use em ícones de elementos que indiquem uma situação ou estado positivo."
        },
        "warning": {
          "value": "{color.surface.warning.strong}",
          "type": "color",
          "description": "Use em ícones de elementos que indiquem um estado de alerta não-crítico."
        },
        "danger": {
          "value": "{color.text.danger.base}",
          "type": "color",
          "description": "Use em ícones de elementos que indiquem uma situação ou estado negativo."
        }
      }
    },
    "utility": {
      "light": {
        "value": "{color.neutral.light}",
        "type": "color",
        "description": "Use quando há necessidade de que a cor se mantenha semprea mesma, independente do tema aplicado à interface."
      },
      "dark": {
        "value": "{color.neutral.dark}",
        "type": "color",
        "description": "Use quando há necessidade de que a cor se mantenha semprea mesma, independente do tema aplicado à interface."
      }
    },
    "shadow": {
      "neutral": {
        "soft": {
          "value": "{color.gray.900}",
          "type": "color",
          "$extensions": {
            "studio.tokens": {
              "modify": {
                "type": "alpha",
                "value": "{opacity.low}",
                "space": "lch"
              }
            }
          },
          "description": "Use em sombras e superfícies semitransparentes, como overlays."
        },
        "intense": {
          "value": "{color.gray.900}",
          "type": "color",
          "$extensions": {
            "studio.tokens": {
              "modify": {
                "type": "alpha",
                "value": "{opacity.medium}",
                "space": "lch"
              }
            }
          },
          "description": "Use em sombras e superfícies semitransparentes, como overlays."
        }
      },
      "accent": {
        "soft": {
          "value": "{color.purple.700}",
          "type": "color",
          "$extensions": {
            "studio.tokens": {
              "modify": {
                "type": "alpha",
                "value": "{opacity.medium}",
                "space": "lch"
              }
            }
          },
          "description": "Use em sombras e superfícies semitransparentes, como overlays."
        },
        "intense": {
          "value": "{color.purple.700}",
          "type": "color",
          "$extensions": {
            "studio.tokens": {
              "modify": {
                "type": "alpha",
                "value": "{opacity.high}",
                "space": "lch"
              }
            }
          },
          "description": "Use em sombras e superfícies semitransparentes, como overlays."
        }
      },
      "info": {
        "soft": {
          "value": "{color.blue.700}",
          "type": "color",
          "$extensions": {
            "studio.tokens": {
              "modify": {
                "type": "alpha",
                "value": "{opacity.medium}",
                "space": "lch"
              }
            }
          },
          "description": "Use em sombras e superfícies semitransparentes, como overlays."
        },
        "intense": {
          "value": "{color.blue.700}",
          "type": "color",
          "$extensions": {
            "studio.tokens": {
              "modify": {
                "type": "alpha",
                "value": "{opacity.high}",
                "space": "lch"
              }
            }
          },
          "description": "Use em sombras e superfícies semitransparentes, como overlays."
        }
      },
      "success": {
        "soft": {
          "value": "{color.green.700}",
          "type": "color",
          "$extensions": {
            "studio.tokens": {
              "modify": {
                "type": "alpha",
                "value": "{opacity.medium}",
                "space": "lch"
              }
            }
          },
          "description": "Use em sombras e superfícies semitransparentes, como overlays."
        },
        "intense": {
          "value": "{color.green.700}",
          "type": "color",
          "$extensions": {
            "studio.tokens": {
              "modify": {
                "type": "alpha",
                "value": "{opacity.high}",
                "space": "lch"
              }
            }
          },
          "description": "Use em sombras e superfícies semitransparentes, como overlays."
        }
      },
      "warning": {
        "soft": {
          "value": "{color.yellow.600}",
          "type": "color",
          "$extensions": {
            "studio.tokens": {
              "modify": {
                "type": "alpha",
                "value": "{opacity.medium}",
                "space": "lch"
              }
            }
          },
          "description": "Use em sombras e superfícies semitransparentes, como overlays."
        },
        "intense": {
          "value": "{color.yellow.600}",
          "type": "color",
          "$extensions": {
            "studio.tokens": {
              "modify": {
                "type": "alpha",
                "value": "{opacity.high}",
                "space": "lch"
              }
            }
          },
          "description": "Use em sombras e superfícies semitransparentes, como overlays."
        }
      },
      "danger": {
        "soft": {
          "value": "{color.red.700}",
          "type": "color",
          "$extensions": {
            "studio.tokens": {
              "modify": {
                "type": "alpha",
                "value": "{opacity.medium}",
                "space": "lch"
              }
            }
          },
          "description": "Use em sombras e superfícies semitransparentes, como overlays."
        },
        "intense": {
          "value": "{color.red.700}",
          "type": "color",
          "$extensions": {
            "studio.tokens": {
              "modify": {
                "type": "alpha",
                "value": "{opacity.high}",
                "space": "lch"
              }
            }
          },
          "description": "Use em sombras e superfícies semitransparentes, como overlays."
        }
      }
    }
  },
  "font": {
    "face": {
      "brand": {
        "value": "Cabinet Grotesk Variable",
        "type": "fontFamilies",
        "description": "Usada em títulos e elementos de interface"
      },
      "body": {
        "value": "{font.face.brand}",
        "type": "fontFamilies",
        "description": "Usada em textos corridos e demais snippets de texto que não correspondem a um elemento de interface"
      },
      "fallback": {
        "value": "system-ui",
        "type": "fontFamilies",
        "description": "Fonte utilizada como último recurso caso as fontes principal e alternativa não estejam disponíveis."
      },
      "family": {
        "value": "sans-serif",
        "type": "fontFamilies",
        "description": "Família de fontes a ser utilizada como último recurso de alternativas."
      }
    },
    "weight": {
      "heading": {
        "value": "{font.weight.bold}",
        "type": "fontWeights",
        "description": "Font-weight padrão para estilos de heading."
      },
      "subtitle": {
        "value": "{font.weight.light}",
        "type": "fontWeights",
        "description": "Font-weight padrão para estilos de subtitle."
      },
      "overline": {
        "value": "{font.weight.bold}",
        "type": "fontWeights",
        "description": "Font-weight padrão para estilos de overline."
      },
      "body": {
        "value": "{font.weight.regular}",
        "type": "fontWeights",
        "description": "Font-weight padrão para estilos de body copy."
      },
      "longform": {
        "value": "{font.weight.regular}",
        "type": "fontWeights",
        "description": "Font-weight padrão para estilos de longform."
      },
      "numbers": {
        "value": "{font.weight.semibold}",
        "type": "fontWeights",
        "description": "Font-weight padrão para estilos de numbers."
      },
      "ui": {
        "value": "{font.weight.semibold}",
        "type": "fontWeights",
        "description": "Font-weight padrão para estilos de elementos de UI."
      }
    },
    "size": {
      "base": {
        "value": "18",
        "type": "fontSizes"
      }
    },
    "scale": {
      "mobile": {
        "value": "{font.scale.major2nd}",
        "type": "number"
      },
      "tablet": {
        "value": "{font.scale.major2nd}",
        "type": "number"
      },
      "desktop": {
        "value": "{font.scale.major3rd}",
        "type": "number"
      }
    }
  }
}